bizyairsdk/__init__.py
bizyairsdk/config.py
bizyairsdk/version.txt
bizyairsdk/encode_decode/__init__.py
bizyairsdk/encode_decode/core.py
bizyairsdk/utils/__init__.py
bizyairsdk/utils/_helpers.py
bizyairsdk/utils/comfy_utils.py
bizyairsdk/utils/conversions.py
bizyairsdk-0.1.4.dist-info/METADATA
bizyairsdk-0.1.4.dist-info/WHEEL
bizyairsdk-0.1.4.dist-info/top_level.txt
bizyairsdk-0.1.4.dist-info/RECORD
